tusclient/__init__.py
tusclient/client.py
tusclient/exceptions.py
tusclient/py.typed
tusclient/request.py
tusclient/fingerprint/__init__.py
tusclient/fingerprint/fingerprint.py
tusclient/fingerprint/interface.py
tusclient/storage/__init__.py
tusclient/storage/filestorage.py
tusclient/storage/interface.py
tusclient/uploader/__init__.py
tusclient/uploader/baseuploader.py
tusclient/uploader/uploader.py
tuspy-1.0.3.dist-info/AUTHORS
tuspy-1.0.3.dist-info/LICENSE
tuspy-1.0.3.dist-info/METADATA
tuspy-1.0.3.dist-info/WHEEL
tuspy-1.0.3.dist-info/top_level.txt
tuspy-1.0.3.dist-info/RECORD
